bhej/__init__.py
bhej/config.py
bhej/main.py
bhej/scripts.py
bhej/utils.py
bhej-0.1.7.dist-info/entry_points.txt
bhej-0.1.7.dist-info/LICENSE
bhej-0.1.7.dist-info/WHEEL
bhej-0.1.7.dist-info/METADATA
bhej-0.1.7.dist-info/RECORD
