Metadata-Version: 2.1
Name: bhej
Version: 0.1.7
Summary: Share files like a dev.
Home-page: https://bhej.dev
License: MIT
Keywords: filesharing,developer tools
Author: ivraj
Author-email: iseerha@gmail.com
Requires-Python: >=3.6.1,<4.0.0
Classifier: Development Status :: 4 - Beta
Classifier: Environment :: Console
Classifier: Intended Audience :: Developers
Classifier: License :: OSI Approved :: MIT License
Classifier: Natural Language :: English
Classifier: Operating System :: OS Independent
Classifier: Programming Language :: Python :: 3
Classifier: Programming Language :: Python :: 3.6
Classifier: Programming Language :: Python :: 3.7
Classifier: Programming Language :: Python :: 3.8
Classifier: Topic :: Communications :: File Sharing
Classifier: Topic :: Scientific/Engineering :: Artificial Intelligence
Requires-Dist: pandas (>=1.1.4,<2.0.0)
Requires-Dist: python-magic (>=0.4.3,<0.5.0); sys_platform == "linux"
Requires-Dist: python-magic-bin (==0.4.14); sys_platform == "win32" or sys_platform == "darwin"
Requires-Dist: requests (>=2.24.0,<3.0.0)
Requires-Dist: requests-toolbelt (>=0.9.1,<0.10.0)
Requires-Dist: tqdm (>=4.51.0,<5.0.0)
Requires-Dist: typer[all] (>=0.3.2,<0.4.0)
Project-URL: Documentation, https://github.com/bhejdev/bhej-cli
Project-URL: Repository, https://github.com/bhejdev/bhej-cli
